shift_reg/shift_reg.srcs/sources_1/new/shift_reg.v
`timescale 1ns / 1ps
//////////////////////////////////////////////////////////////////////////////////
// Company: 
// Engineer: 
// 
// Create Date: 19.10.2023 10:47:02
// Design Name: 
// Module Name: shift_reg
// Project Name: 
// Target Devices: 
// Tool Versions: 
// Description: 
// 
// Dependencies: 
// 
// Revision:
// Revision 0.01 - File Created
// Additional Comments:
// 
//////////////////////////////////////////////////////////////////////////////////


module univshift(in,cnt,clk,rst,q);
  input clk,rst;
  input [3:0]in;
  input [1:0]cnt;
  output reg [3:0]q;
  
  always @(posedge clk,posedge rst)
    begin
      if(rst)
        q<=0;
      else
        begin
          case(cnt)
            2'b00: q<=q;
              
            2'b01: q<={1'b0,q[3:1]};
              
            2'b10: q<={q[2:0],1'b0};
              
            2'b11: q<= in;
              
              default: q<=0;
          endcase
        end
    end
endmodule

shift_reg/shift_reg.srcs/sim_1/new/shitf_reg_tb.v
`timescale 1ns / 1ps
//////////////////////////////////////////////////////////////////////////////////
// Company: 
// Engineer: 
// 
// Create Date: 19.10.2023 10:55:06
// Design Name: 
// Module Name: shitf_reg_tb
// Project Name: 
// Target Devices: 
// Tool Versions: 
// Description: 
// 
// Dependencies: 
// 
// Revision:
// Revision 0.01 - File Created
// Additional Comments:
// 
//////////////////////////////////////////////////////////////////////////////////


module univshifttb();
  reg clk,rst;
  reg [3:0] in;
  reg [1:0] cnt;
  wire [3:0] q;
  
  univshift dut(in,cnt,clk,rst,q);
  initial 
    begin
      clk = 1;
      forever #5 clk = ~clk;
    end
  
  initial 
    begin
      $dumpfile("univshifttb.vcd");
      $dumpvars(0,univshifttb);
      #200 $finish;
    end
  
  initial
    begin
      rst=1;
      #10 rst=0; cnt=2'b11; in=4'b1100;
      #10 cnt=2'b00;
      #10 cnt=2'b01;
      #30 cnt=2'b11; in=4'b1100;
      #10 cnt=2'b10;
      #30 rst=1;
    end
endmodule

shift_reg/shift_reg.sim/sim_1/behav/xsim/univshifttb.vcd
$date
   Thu Oct 19 11:11:07 2023
$end
$version
  2018.3
$end
$timescale
  1ps
$end
$scope module univshifttb $end
$var reg 1 ! clk $end
$var reg 1 " rst $end
$var reg 4 # in [3:0] $end
$var reg 2 $ cnt [1:0] $end
$var wire 4 % q [3:0] $end
$scope module dut $end
$var wire 1 & clk $end
$var wire 1 ' rst $end
$var wire 4 ( in [3:0] $end
$var wire 2 ) cnt [1:0] $end
$var reg 4 * q [3:0] $end
$upscope $end
$upscope $end
$enddefinitions $end
#0
$dumpvars
1!
1"
bx #
bx $
b0 %
1&
1'
bx (
bx )
b0 *
$end
#5000
0!
0&
#10000
1!
0"
b1100 #
b11 $
b1100 %
1&
0'
b1100 (
b11 )
b1100 *
#15000
0!
0&
#20000
1!
b0 $
1&
b0 )
#25000
0!
0&
#30000
1!
b1 $
b110 %
1&
b1 )
b110 *
#35000
0!
0&
#40000
1!
b11 %
1&
b11 *
#45000
0!
0&
#50000
1!
b1 %
1&
b1 *
#55000
0!
0&
#60000
1!
b1100 #
b11 $
b1100 %
1&
b11 )
b1100 *
#65000
0!
0&
#70000
1!
b10 $
b1000 %
1&
b10 )
b1000 *
#75000
0!
0&
#80000
1!
b0 %
1&
b0 *
#85000
0!
0&
#90000
1!
1&
#95000
0!
0&
#100000
1!
1"
1&
1'
